mb_commons/__init__.py
mb_commons/concurrency.py
mb_commons/date.py
mb_commons/dict.py
mb_commons/dotenv.py
mb_commons/http.py
mb_commons/logging.py
mb_commons/mongo.py
mb_commons/net.py
mb_commons/result.py
mb_commons/shell.py
mb_commons/str.py
mb_commons-1.1.8.dist-info/METADATA
mb_commons-1.1.8.dist-info/WHEEL
mb_commons-1.1.8.dist-info/top_level.txt
mb_commons-1.1.8.dist-info/RECORD
